JupyterToLib/__init__.py
JupyterToLib/jupyter_to_py.py
JupyterToLib-0.1.dist-info/METADATA
JupyterToLib-0.1.dist-info/WHEEL
JupyterToLib-0.1.dist-info/top_level.txt
JupyterToLib-0.1.dist-info/RECORD
