Metadata-Version: 2.1
Name: JupyterToLib
Version: 0.1
Summary: A Python package that transforms your Jupyter notebooks into Python modules and optimizes your scripts by removing comments and empty lines.
Home-page: https://github.com/jcval94/JupyterToLib.git
Author: Jose Carlos Del Valle
Author-email: jcvsl94@gmail.com
Requires-Dist: nbformat (>=5.1.3)
Requires-Dist: ast
Requires-Dist: json
Requires-Dist: re
